rxn/onmt_utils/__init__.py
rxn/onmt_utils/internal_translation_utils.py
rxn/onmt_utils/model_introspection.py
rxn/onmt_utils/model_resize.py
rxn/onmt_utils/py.typed
rxn/onmt_utils/strip_model.py
rxn/onmt_utils/torch_utils.py
rxn/onmt_utils/train_command.py
rxn/onmt_utils/translate.py
rxn/onmt_utils/translator.py
rxn/onmt_utils/scripts/__init__.py
rxn/onmt_utils/scripts/extend_model_with_vocab.py
rxn/onmt_utils/scripts/translate.py
rxn_onmt_utils-1.1.0.dist-info/LICENSE
rxn_onmt_utils-1.1.0.dist-info/METADATA
rxn_onmt_utils-1.1.0.dist-info/WHEEL
rxn_onmt_utils-1.1.0.dist-info/entry_points.txt
rxn_onmt_utils-1.1.0.dist-info/top_level.txt
rxn_onmt_utils-1.1.0.dist-info/RECORD
