Metadata-Version: 2.1
Name: rxn-onmt-utils
Version: 1.1.0
Summary: Utilities related to the use of OpenNMT
Home-page: https://github.com/rxn4chemistry/rxn-onmt-utils
Author: IBM RXN team
License: MIT
Project-URL: Documentation, https://rxn4chemistry.github.io/rxn-onmt-utils/
Project-URL: Repository, https://github.com/rxn4chemistry/rxn-onmt-utils
Classifier: Operating System :: OS Independent
Classifier: Programming Language :: Python :: 3
Classifier: Programming Language :: Python :: 3.6
Requires-Python: >=3.6
License-File: LICENSE
Requires-Dist: attrs >=21.2.0
Requires-Dist: click >=8.0
Requires-Dist: rxn-opennmt-py >=1.1.1
Requires-Dist: rxn-utils >=1.6.0
Provides-Extra: dev
Requires-Dist: black >=22.3.0 ; extra == 'dev'
Requires-Dist: bump2version >=1.0.1 ; extra == 'dev'
Requires-Dist: flake8 >=3.8.4 ; extra == 'dev'
Requires-Dist: isort >=5.10.1 ; extra == 'dev'
Requires-Dist: mypy >=0.910 ; extra == 'dev'
Requires-Dist: types-setuptools >=57.4.14 ; extra == 'dev'
